{
    "title": "Get user infomation",
    "endpoint": "/users/:user_id",
    "method": "get",
    "request": null,
    "response": [
        {
            "status": 200,
            "data": {
                "user": {
                    "name": "smk0107",
                    "email": "ansrl0107@gmail.com",
                    "birthday": "1998-01-06T15:00:00.000Z",
                    "introduce": null,
                    "gender": "M",
                    "points": 0,
                    "profile": "api.gamepicker.co.kr/uploads/eyJ0eXAiOiJKV1QiLCJhbGciOiJIUzI1NiJ9.eyJ1c2VyX2lkIjo5Nywib2JqZWN0IjoicHJvZmlsZSJ9.LrSSTXEznYqjphox8kriwDM5HfrujR2j_D-SPMLLYEU.jpg"
                }
            }
        }
    ]
}